skywalking_trace/__init__.py
skywalking_trace/functiongraph_trace.py
skywalking_trace/scf_trace.py
skywalking_trace/trace_log.py
skywalking_trace-1.2.1.dist-info/LICENSE
skywalking_trace-1.2.1.dist-info/METADATA
skywalking_trace-1.2.1.dist-info/WHEEL
skywalking_trace-1.2.1.dist-info/top_level.txt
skywalking_trace-1.2.1.dist-info/RECORD
