Metadata-Version: 2.1
Name: skywalking-trace
Version: 1.2.1
Summary: skywalking trace print log  tool
Author-email: "xiaodong.yang" <yymagicer@163.com>
Project-URL: Homepage, https://gitee.com/yymagicer/skywalking_trace.git
Project-URL: Bug Tracker, https://gitee.com/yymagicer/skywalking_trace.git/issues
Classifier: Programming Language :: Python :: 3
Classifier: License :: OSI Approved :: MIT License
Requires-Python: >=3.9
License-File: LICENSE
